aiodeu/__init__.py
aiodeu/app.py
aiodeu/cetl.pyx
aiodeu/codecs.py
aiodeu/config.py
aiodeu/console.py
aiodeu/etl.py
aiodeu/logger.py
aiodeu/s3.py
aiodeu/utils.py
aiodeu/cetl.cpython-310-darwin.so
aiodeu/cetl.c
aiodeu-0.1.29.dist-info/LICENSE
aiodeu-0.1.29.dist-info/WHEEL
aiodeu-0.1.29.dist-info/entry_points.txt
aiodeu-0.1.29.dist-info/METADATA
aiodeu-0.1.29.dist-info/RECORD
